syncode/__init__.py
syncode/common.py
syncode/dataset.py
syncode/grammar_decoder.py
syncode/infer.py
syncode/language_model.py
syncode/parse_result.py
syncode/process_eval.py
syncode/evaluation/__init__.py
syncode/evaluation/code_eval.py
syncode/evaluation/fol_eval.py
syncode/evaluation/json_eval.py
syncode/evaluation/math_eval.py
syncode/evaluation/mxeval_evaluation.py
syncode/evaluation/sql_eval.py
syncode/evaluation/mxeval/__init__.py
syncode/evaluation/mxeval/data.py
syncode/evaluation/mxeval/evaluate_functional_correctness.py
syncode/evaluation/mxeval/evaluation.py
syncode/evaluation/mxeval/execution.py
syncode/larkm/__init__.py
syncode/larkm/ast_utils.py
syncode/larkm/common.py
syncode/larkm/exceptions.py
syncode/larkm/grammar.py
syncode/larkm/indenter.py
syncode/larkm/lark.py
syncode/larkm/lexer.py
syncode/larkm/load_grammar.py
syncode/larkm/parse_tree_builder.py
syncode/larkm/parser_frontends.py
syncode/larkm/py.typed
syncode/larkm/reconstruct.py
syncode/larkm/tree.py
syncode/larkm/tree_matcher.py
syncode/larkm/tree_templates.py
syncode/larkm/utils.py
syncode/larkm/visitors.py
syncode/larkm/__pyinstaller/__init__.py
syncode/larkm/__pyinstaller/hook-lark.py
syncode/larkm/grammars/__init__.py
syncode/larkm/grammars/common.lark
syncode/larkm/grammars/lark.lark
syncode/larkm/grammars/python.lark
syncode/larkm/grammars/unicode.lark
syncode/larkm/parsers/__init__.py
syncode/larkm/parsers/cyk.py
syncode/larkm/parsers/earley.py
syncode/larkm/parsers/earley_common.py
syncode/larkm/parsers/earley_forest.py
syncode/larkm/parsers/grammar_analysis.py
syncode/larkm/parsers/lalr_analysis.py
syncode/larkm/parsers/lalr_interactive_parser.py
syncode/larkm/parsers/lalr_parser_state.py
syncode/larkm/parsers/lr_parsers.py
syncode/larkm/parsers/xearley.py
syncode/larkm/tools/__init__.py
syncode/larkm/tools/nearley.py
syncode/larkm/tools/serialize.py
syncode/larkm/tools/standalone.py
syncode/mask_store/__init__.py
syncode/mask_store/byte_fsm.py
syncode-0.4.0.dist-info/LICENSE
syncode-0.4.0.dist-info/METADATA
syncode-0.4.0.dist-info/WHEEL
syncode-0.4.0.dist-info/top_level.txt
syncode-0.4.0.dist-info/RECORD
