Metadata-Version: 2.2
Name: syncode
Version: 0.4.0
Summary: Grammar-guided code generation tool
Home-page: https://github.com/uiuc-focal-lab/syncode
Author: Shubham Ugare
Author-email: Shubham Ugare <shubhamugare@gmail.com>
License: MIT
Project-URL: Homepage, https://github.com/shubhamugare/syncode
Project-URL: Bug Tracker, https://github.com/shubhamugare/syncode/issues
Classifier: Programming Language :: Python :: 3
Classifier: Intended Audience :: Science/Research
Classifier: License :: OSI Approved :: MIT License
Classifier: Operating System :: OS Independent
License-File: LICENSE
Requires-Dist: fire
Requires-Dist: interegular
Requires-Dist: regex==2023.8.8
Requires-Dist: torch
Requires-Dist: tqdm
Requires-Dist: transformers==4.44.0
Requires-Dist: datasets
Requires-Dist: jsonschema
Dynamic: author
Dynamic: home-page
